jsv/__init__.py
jsv/__version__.py
jsv/template.py
jsv/template_io.py
jsv-0.1.1.data/data/LICENSE
jsv-0.1.1.dist-info/LICENSE
jsv-0.1.1.dist-info/METADATA
jsv-0.1.1.dist-info/WHEEL
jsv-0.1.1.dist-info/top_level.txt
jsv-0.1.1.dist-info/zip-safe
jsv-0.1.1.dist-info/RECORD
